setup.py
flaxcrf/__init__.py
flaxcrf.egg-info/PKG-INFO
flaxcrf.egg-info/SOURCES.txt
flaxcrf.egg-info/dependency_links.txt
flaxcrf.egg-info/top_level.txt