Metadata-Version: 2.1
Name: flaxcrf
Version: 0.1.0
Summary: Conditional random field in JAX
Home-page: https://github.com/alao/flaxcrf.git
Author: jimmy
Author-email: alao556@live.com
License: Apache-2.0
Keywords: jax
Classifier: Programming Language :: Python :: 3.7
Classifier: Programming Language :: Python :: 3.8
Classifier: Programming Language :: Python :: 3.9
Classifier: Programming Language :: Python :: 3.10
Requires-Python: >=3.7
